soapbox/__init__.py
soapbox/admin.py
soapbox/context_processors.py
soapbox/models.py
soapbox/fixtures/soapboxtest.json
soapbox/migrations/0001_initial.py
soapbox/migrations/0002_is_global_default.py
soapbox/migrations/__init__.py
soapbox/templatetags/__init__.py
soapbox/templatetags/soapbox.py
django_soapbox-1.6.1.dist-info/LICENSE
django_soapbox-1.6.1.dist-info/METADATA
django_soapbox-1.6.1.dist-info/WHEEL
django_soapbox-1.6.1.dist-info/top_level.txt
django_soapbox-1.6.1.dist-info/RECORD
